galadriel_node/__init__.py
galadriel_node/cli/app.py
galadriel_node/cli/network.py
galadriel_node/cli/node.py
galadriel_node/config.py
galadriel_node/config_initialiser.py
galadriel_node/llm_backends/vllm.py
galadriel_node/sdk/api.py
galadriel_node/sdk/datasets/ai_wiki_8k.txt
galadriel_node/sdk/datasets/im_feeling_curious.jsonl
galadriel_node/sdk/diffusers.py
galadriel_node/sdk/entities.py
galadriel_node/sdk/image_generation.py
galadriel_node/sdk/jobs/api_ping_job.py
galadriel_node/sdk/jobs/reconnect_request_job.py
galadriel_node/sdk/llm.py
galadriel_node/sdk/logging_utils.py
galadriel_node/sdk/long_benchmark.py
galadriel_node/sdk/protocol/entities.py
galadriel_node/sdk/protocol/health_check_protocol.py
galadriel_node/sdk/protocol/ping_pong_protocol.py
galadriel_node/sdk/protocol/protocol_handler.py
galadriel_node/sdk/protocol/protocol_settings.py
galadriel_node/sdk/system/entities.py
galadriel_node/sdk/system/report_hardware.py
galadriel_node/sdk/system/report_performance.py
galadriel_node/sdk/system/report_utilization.py
galadriel_node/sdk/time_tracker.py
galadriel_node/sdk/upgrade.py
galadriel_node/sdk/util/locked_counter.py
galadriel_node-0.0.19.dist-info/METADATA
galadriel_node-0.0.19.dist-info/WHEEL
galadriel_node-0.0.19.dist-info/entry_points.txt
galadriel_node-0.0.19.dist-info/RECORD
