Metadata-Version: 2.1
Name: galadriel-node
Version: 0.0.19
Summary: 
Author: Kaspar Peterson
Author-email: kaspar@galadriel.com
Requires-Python: >=3.10,<4.0
Classifier: Programming Language :: Python :: 3
Classifier: Programming Language :: Python :: 3.10
Classifier: Programming Language :: Python :: 3.11
Classifier: Programming Language :: Python :: 3.12
Classifier: Programming Language :: Python :: 3.13
Provides-Extra: dev
Requires-Dist: accelerate (>=1.1.0,<2.0.0)
Requires-Dist: aiohttp (>=3.10.5,<4.0.0)
Requires-Dist: black (>=24.8.0,<25.0.0) ; extra == "dev"
Requires-Dist: dataclasses-json (>=0.6.7,<0.7.0)
Requires-Dist: diffusers (>=0.31.0,<0.32.0)
Requires-Dist: fastapi (>=0.115.0,<0.116.0)
Requires-Dist: gpustat (>=1.1.1,<2.0.0)
Requires-Dist: openai (>=1.55.3,<2.0.0)
Requires-Dist: ping3 (>=4.0.8,<5.0.0)
Requires-Dist: psutil (>=6.0.0,<7.0.0)
Requires-Dist: py-cpuinfo (>=9.0.0,<10.0.0)
Requires-Dist: pytest (>=8.3.2,<9.0.0) ; extra == "dev"
Requires-Dist: pytest-asyncio (==0.24.0) ; extra == "dev"
Requires-Dist: pytest-mock (>=3.14.0,<4.0.0) ; extra == "dev"
Requires-Dist: python-dotenv (>=1.0.1,<2.0.0)
Requires-Dist: requests (==2.31.0)
Requires-Dist: speedtest-cli (>=2.1.3,<3.0.0)
Requires-Dist: transformers (>=4.0.0,<5.0.0)
Requires-Dist: typer (>=0.12.3,<0.13.0)
Requires-Dist: vllm (==0.6.4.post1) ; sys_platform == "linux"
Requires-Dist: websockets (>=13.0,<14.0)
